LICENSE
MANIFEST.in
README.md
setup.cfg
setup.py
drf_encrypt_content/__init__.py
drf_encrypt_content/mixins.py
drf_encrypt_content/rest_encrypt_content.py
drf_encrypt_content/serializers.py
drf_encrypt_content.egg-info/PKG-INFO
drf_encrypt_content.egg-info/SOURCES.txt
drf_encrypt_content.egg-info/dependency_links.txt
drf_encrypt_content.egg-info/requires.txt
drf_encrypt_content.egg-info/top_level.txt
drf_encrypt_content/management/__init__.py
drf_encrypt_content/management/commands/__init__.py
drf_encrypt_content/management/commands/generate_key.py
drf_encrypt_content/tests/__init__.py